doc/conf.py
donfig/__init__.py
donfig/_lock.py
donfig/config_obj.py
donfig/utils.py
donfig/version.py
donfig/tests/__init__.py
donfig/tests/test_config.py
donfig/tests/test_lock.py
donfig-0.8.1.post0.dist-info/AUTHORS.md
donfig-0.8.1.post0.dist-info/LICENSE.txt
donfig-0.8.1.post0.dist-info/METADATA
donfig-0.8.1.post0.dist-info/WHEEL
donfig-0.8.1.post0.dist-info/top_level.txt
donfig-0.8.1.post0.dist-info/RECORD
