Metadata-Version: 2.1
Name: donfig
Version: 0.8.1.post0
Summary: Python package for configuring a python package
Maintainer-email: David Hoese <david.hoese@ssec.wisc.edu>
License: MIT
Project-URL: Homepage, https://github.com/pytroll/donfig
Keywords: task-scheduling parallel numpy pandas pydata
Classifier: Development Status :: 3 - Alpha
Classifier: Intended Audience :: Developers
Classifier: License :: OSI Approved :: MIT License
Classifier: Operating System :: OS Independent
Classifier: Programming Language :: Python
Classifier: Topic :: Scientific/Engineering
Requires-Python: >=3.8
License-File: LICENSE.txt
License-File: AUTHORS.md
Requires-Dist: pyyaml
Provides-Extra: test
Requires-Dist: pytest; extra == "test"
Requires-Dist: cloudpickle; extra == "test"
Provides-Extra: docs
Requires-Dist: sphinx>=4.0.0; extra == "docs"
Requires-Dist: numpydoc; extra == "docs"
Requires-Dist: pytest; extra == "docs"
Requires-Dist: cloudpickle; extra == "docs"
